kofconfig.py
setup.py
kofconfig.egg-info/PKG-INFO
kofconfig.egg-info/SOURCES.txt
kofconfig.egg-info/dependency_links.txt
kofconfig.egg-info/entry_points.txt
kofconfig.egg-info/top_level.txt