Metadata-Version: 1.1
Name: kofconfig
Version: 0.1.1
Summary: KOF Keyboard Config Tool for MAME OS X
Home-page: https://github.com/mitnk/kofconfig
Author: mitnk
Author-email: w@mitnk.com
License: MIT
Keywords: KOF MAME keyboard
Platform: UNKNOWN
Classifier: Development Status :: 4 - Beta
Classifier: Intended Audience :: Developers
Classifier: Topic :: Software Development :: Build Tools
Classifier: License :: OSI Approved :: MIT License
Classifier: Programming Language :: Python :: 2.7
Classifier: Programming Language :: Python :: 3
Classifier: Programming Language :: Python :: 3.4
Classifier: Programming Language :: Python :: 3.5
